spryx_billin/__init__.py
spryx_billin/client.py
spryx_billin/resources/__init__.py
spryx_billin/resources/credit_balances.py
spryx_billin/resources/credit_cards.py
spryx_billin/resources/credit_pricing.py
spryx_billin/resources/features.py
spryx_billin/resources/invoices.py
spryx_billin/resources/org_customers.py
spryx_billin/resources/plans.py
spryx_billin/resources/stripe.py
spryx_billin/resources/subscriptions.py
spryx_billin/resources/webhooks.py
spryx_billin/types/__init__.py
spryx_billin/types/billing.py
spryx_billin-0.1.1.dist-info/LICENSE
spryx_billin-0.1.1.dist-info/METADATA
spryx_billin-0.1.1.dist-info/WHEEL
spryx_billin-0.1.1.dist-info/RECORD
