Metadata-Version: 2.3
Name: spryx-billin
Version: 0.1.1
Summary: 
Author: Luiz H. R. Gomes
Author-email: luiz@spryx.ai
Requires-Python: >=3.11
Classifier: Programming Language :: Python :: 3
Classifier: Programming Language :: Python :: 3.11
Classifier: Programming Language :: Python :: 3.12
Classifier: Programming Language :: Python :: 3.13
Requires-Dist: spryx-http (>=0.1.7,<0.2.0)
